repcomp/__init__.py
repcomp/comparison.py
repcomp/embedding_source.py
repcomp/exceptions.py
repcomp/neighbors.py
repcomp-0.1.dist-info/LICENSE
repcomp-0.1.dist-info/METADATA
repcomp-0.1.dist-info/WHEEL
repcomp-0.1.dist-info/top_level.txt
repcomp-0.1.dist-info/RECORD
