Metadata-Version: 2.1
Name: repcomp
Version: 0.1
Summary: A package for comparing trained embedding models.
Home-page: https://github.com/pypa/sampleproject
Author: Dan Shiebler
Author-email: danshiebler@gmail.com
License: UNKNOWN
Platform: UNKNOWN
Classifier: Programming Language :: Python :: 3
Classifier: License :: OSI Approved :: MIT License
Classifier: Operating System :: OS Independent
Requires-Dist: pandas (>=0.20.3)
Requires-Dist: gensim (>=0.13.3)
Requires-Dist: keras (>=2.0.1)
Requires-Dist: annoy (>=1.12.0)
Requires-Dist: mock (>=2.0.0)
Requires-Dist: tqdm (>=4.19.5)
Requires-Dist: scikit-learn (>=0.19.1)
Requires-Dist: pytest (>=3.4.1)
